app/__init__.py
app/__main__.py
app/config.py
app/controllers/__init__.py
app/controllers/base_controller.py
app/controllers/generate_controller.py
app/loaders/__init__.py
app/loaders/postman_loader.py
app/services/__init__.py
app/services/generator_service.py
app/services/loader_service.py
app/services/mock_service.py
mockgen-0.0.1.dist-info/DESCRIPTION.rst
mockgen-0.0.1.dist-info/METADATA
mockgen-0.0.1.dist-info/RECORD
mockgen-0.0.1.dist-info/WHEEL
mockgen-0.0.1.dist-info/entry_points.txt
mockgen-0.0.1.dist-info/metadata.json
mockgen-0.0.1.dist-info/top_level.txt
