Metadata-Version: 2.0
Name: mockgen
Version: 0.0.1
Summary: A foundation made with cement
Home-page: https://github.com/jamrizzi/foundation
Author: Jam Risser
Author-email: jam@jamrizzi.com
License: MIT
Keywords: cli foundation sync symlink command line interface
Platform: UNKNOWN
Classifier: Development Status :: 4 - Beta
Classifier: Intended Audience :: Developers
Classifier: Topic :: Utilities
Classifier: License :: OSI Approved :: MIT License
Classifier: Programming Language :: Python :: 2
Classifier: Programming Language :: Python :: 2.7
Classifier: Programming Language :: Python :: 3
Classifier: Programming Language :: Python :: 3.3
Classifier: Programming Language :: Python :: 3.4
Classifier: Programming Language :: Python :: 3.5
Requires-Dist: cement (==2.10.2)
Requires-Dist: certifi (==2017.7.27.1)
Requires-Dist: chardet (==3.0.4)
Requires-Dist: idna (==2.6)
Requires-Dist: Jinja2 (==2.9.6)
Requires-Dist: MarkupSafe (==1.0)
Requires-Dist: pydash (==4.2.1)
Requires-Dist: requests (==2.18.4)
Requires-Dist: urllib3 (==1.22)
